modify_subs.libs/libpng15-ce838cd1.so.15.13.0
modify_subs.libs/libass-24c73fe2.so.5.3.2
modify_subs.libs/libgraphite2-3fca41c8.so.3.0.1
modify_subs.libs/libbz2-a273e504.so.1.0.6
modify_subs.libs/libharfbuzz-77c15733.so.0.10705.0
modify_subs.libs/libjsoncpp-32237a6b.so.0.10.5
modify_subs.libs/libfribidi-56e75413.so.0.4.0
modify_subs.libs/libuuid-f64cda11.so.1.3.0
modify_subs.libs/libfontconfig-42c558d2.so.1.11.1
modify_subs.libs/libfreetype-c0e61f0c.so.6.14.0
modify_subs-0.5.2.dist-info/top_level.txt
modify_subs-0.5.2.dist-info/RECORD
modify_subs-0.5.2.dist-info/METADATA
modify_subs-0.5.2.dist-info/WHEEL
c_delocalizer/modify_subs.cpython-39-x86_64-linux-gnu.so
c_delocalizer/pair_subs.cpython-39-x86_64-linux-gnu.so
